ChangeLog
LICENSE.txt
README.txt
TODO
setup.py
sdecstr/__init__.py
sdecstr/sa.py
sdecstr/sa.txt
sdecstr/sdecstr.txt
sdecstr/test.py
sdecstr.egg-info/PKG-INFO
sdecstr.egg-info/SOURCES.txt
sdecstr.egg-info/dependency_links.txt
sdecstr.egg-info/top_level.txt