Metadata-Version: 1.0
Name: sdecstr
Version: 0.0.1
Summary: Decimal datatype stored as a signed string, enabling rich comparisons.
Home-page: UNKNOWN
Author: Hermann Himmelbauer
Author-email: dusty@qwer.tk
License: LGPL
Platform: UNKNOWN
